aspen_pystache.py
distribute_setup.py
setup.py
aspen_pystache.egg-info/PKG-INFO
aspen_pystache.egg-info/SOURCES.txt
aspen_pystache.egg-info/dependency_links.txt
aspen_pystache.egg-info/entry_points.txt
aspen_pystache.egg-info/not-zip-safe
aspen_pystache.egg-info/requires.txt
aspen_pystache.egg-info/top_level.txt